hideocardgames/__init__.py
hideocardgames/deck.py
hideocardgames/blackjack/__init__.py
hideocardgames/blackjack/game.py
hideocardgames/highlow/__init__.py
hideocardgames/highlow/game.py
tests/__init__.py
tests/test_blackjack_game.py
tests/test_deck.py
tests/test_highlow_game.py
hideocardgames-0.1.0.dist-info/METADATA
hideocardgames-0.1.0.dist-info/WHEEL
hideocardgames-0.1.0.dist-info/top_level.txt
hideocardgames-0.1.0.dist-info/RECORD
